<?xml version="1.0"?>
<!DOCTYPE hibernate-mapping PUBLIC "-//Hibernate/Hibernate Mapping DTD 3.0//EN"
                                   "http://hibernate.sourceforge.net/hibernate-mapping-3.0.dtd">
<!-- Generated 2015-1-7 21:46:33 by Hibernate Tools 3.4.0.CR1 -->
<hibernate-mapping>
 <class name="model.Offer" table="Offer">
  <id length="11" name="OFFER_ID" type="int">
  <property name="offerID" type="int">
   <column name="OFFER_ID"/>
  </property>
  </id>
  <property name="userID" type="int">
   <column name="USER_ID"/>
  </property>
  <property name="sellerFrom" type="int">
   <column name="SELLER_FROM"/>
  </property>
  <property name="sellerTo" type="int">
   <column name="SELLER_TO"/>
  </property>
  <property name="pointsFrom" type="int">
   <column name="POINTS_FROM"/>
  </property>
  <property name="pointsToMin" type="int">
   <column name="POINTS_TO_MIN"/>
  </property>
  <property name="status" type="int">
   <column name="STATUS"/>
 </property>
 </class>
</hibernate-mapping>
